sphinxcontrib/scm/__init__.py
sphinxcontrib/scm/directives.py
sphinxcontrib/scm/roles.py
sphinxcontrib/scm/util.py
sphinxcontrib_scm-0.1.5.dist-info/LICENSE
sphinxcontrib_scm-0.1.5.dist-info/METADATA
sphinxcontrib_scm-0.1.5.dist-info/WHEEL
sphinxcontrib_scm-0.1.5.dist-info/top_level.txt
sphinxcontrib_scm-0.1.5.dist-info/RECORD
