Metadata-Version: 2.1
Name: sphinxcontrib-scm
Version: 0.1.5
Summary: Sphinx SCM interface
Home-page: https://github.com/sphinx-contrib/scm
Download-URL: http://pypi.python.org/pypi/sphinxcontrib-scm
Author: Christian Knittl-Frank
Author-email: lcnittl@gmail.com
License: GPL-3.0
Project-URL: GitHub: repo, https://github.com/sphinx-contrib/scm
Project-URL: GitHub: issues, https://github.com/sphinx-contrib/scm/issues
Classifier: Development Status :: 3 - Alpha
Classifier: Environment :: Console
Classifier: Environment :: Web Environment
Classifier: Framework :: Sphinx :: Extension
Classifier: Intended Audience :: Developers
Classifier: License :: OSI Approved :: GNU General Public License v3 (GPLv3)
Classifier: License :: OSI Approved :: GNU General Public License v3 or later (GPLv3+)
Classifier: Operating System :: OS Independent
Classifier: Programming Language :: Python :: 3
Classifier: Programming Language :: Python :: 3 :: Only
Classifier: Topic :: Documentation :: Sphinx
Classifier: Topic :: Utilities
Requires-Python: >=3.8
License-File: LICENSE
Requires-Dist: Sphinx >=1.8
Requires-Dist: gitpython >=3.1.8
